<?xml version="1.0" encoding="UTF-8"?>
<report><user>agentesslufrgs</user><uuid>1a164c1b-9529-400b-b768-4fe50932669f</uuid><timestamp>1443443169</timestamp><agent_type>linux</agent_type><meas_uuid></meas_uuid><droidVersion>14.04</droidVersion><version>6.1.3</version><results><video_information><ip>::ffff:127.0.0.1</ip><start_timestamp>1443443165139</start_timestamp><hash>zomJCZiwX0w8ZMdXDRSXkosDnMNLpBKcjzVeBhtD6qU0t0aQZwA71Sa2Ztgpc43t</hash><total_played_time>8.425761999999988</total_played_time><total_played_time_with_stall>8.688761999999988</total_played_time_with_stall><total_stall_length>0.263</total_stall_length><total_number_of_stall>1</total_number_of_stall><video_duration>178.214</video_duration><dropped_frames>0</dropped_frames><left_time>146.378569</left_time><video_preload>auto</video_preload><video_start_time>0</video_start_time><netmetric></netmetric><video_information_id>24</video_information_id></video_information><video_source><multiple_entry><source>http://0.0.0.0:3000/tests</source><video_information_id>24</video_information_id></multiple_entry><multiple_entry><source>http://0.0.0.0:3000/resources/hobbit-1080p-01.mp4</source><video_information_id>24</video_information_id></multiple_entry></video_source><volume_state><current_video_position>143.220785</current_video_position><timestamp_of_volume>1443443166146</timestamp_of_volume><video_information_id>24</video_information_id><volume>1</volume></volume_state><video_bytes_decoded_per_second><multiple_entry><current_video_position>143.220785</current_video_position><timestamp_of_video_bytes_decoded>1443443166146</timestamp_of_video_bytes_decoded><video_information_id>24</video_information_id><video_bytes>4237815</video_bytes></multiple_entry><multiple_entry><current_video_position>144.242421</current_video_position><timestamp_of_video_bytes_decoded>1443443167146</timestamp_of_video_bytes_decoded><video_information_id>24</video_information_id><video_bytes>219527</video_bytes></multiple_entry><multiple_entry><current_video_position>145.240838</current_video_position><timestamp_of_video_bytes_decoded>1443443168146</timestamp_of_video_bytes_decoded><video_information_id>24</video_information_id><video_bytes>217859</video_bytes></multiple_entry><multiple_entry><current_video_position>146.239255</current_video_position><timestamp_of_video_bytes_decoded>1443443169147</timestamp_of_video_bytes_decoded><video_information_id>24</video_information_id><video_bytes>254941</video_bytes></multiple_entry></video_bytes_decoded_per_second><audio_bytes_decoded_per_second><multiple_entry><current_video_position>143.220785</current_video_position><timestamp_of_audio_bytes_decoded>1443443166146</timestamp_of_audio_bytes_decoded><video_information_id>24</video_information_id><audio_bytes>439417</audio_bytes></multiple_entry><multiple_entry><current_video_position>144.242421</current_video_position><timestamp_of_audio_bytes_decoded>1443443167146</timestamp_of_audio_bytes_decoded><video_information_id>24</video_information_id><audio_bytes>32385</audio_bytes></multiple_entry><multiple_entry><current_video_position>145.240838</current_video_position><timestamp_of_audio_bytes_decoded>1443443168146</timestamp_of_audio_bytes_decoded><video_information_id>24</video_information_id><audio_bytes>31650</audio_bytes></multiple_entry><multiple_entry><current_video_position>146.239255</current_video_position><timestamp_of_audio_bytes_decoded>1443443169147</timestamp_of_audio_bytes_decoded><video_information_id>24</video_information_id><audio_bytes>31650</audio_bytes></multiple_entry></audio_bytes_decoded_per_second><time_in_buffer><multiple_entry><current_video_position>143.220785</current_video_position><timestamp_of_time>1443443166146</timestamp_of_time><video_information_id>24</video_information_id><remaining_time_in_buffer>34.99321499999999</remaining_time_in_buffer></multiple_entry><multiple_entry><current_video_position>144.242421</current_video_position><timestamp_of_time>1443443167146</timestamp_of_time><video_information_id>24</video_information_id><remaining_time_in_buffer>33.97157899999999</remaining_time_in_buffer></multiple_entry><multiple_entry><current_video_position>145.240838</current_video_position><timestamp_of_time>1443443168146</timestamp_of_time><video_information_id>24</video_information_id><remaining_time_in_buffer>32.973162</remaining_time_in_buffer></multiple_entry><multiple_entry><current_video_position>146.239255</current_video_position><timestamp_of_time>1443443169147</timestamp_of_time><video_information_id>24</video_information_id><remaining_time_in_buffer>31.974744999999984</remaining_time_in_buffer></multiple_entry></time_in_buffer><skip_play><current_video_position>0</current_video_position><timestamp_of_skip>1443443165140</timestamp_of_skip><skip_duration>142.64031</skip_duration><video_information_id>24</video_information_id></skip_play><played_interval><multiple_entry><start_play>0</start_play><end_play>1.531907</end_play><video_information_id>24</video_information_id></multiple_entry><multiple_entry><start_play>35.6428</start_play><end_play>36.454918</end_play><video_information_id>24</video_information_id></multiple_entry><multiple_entry><start_play>71.2856</start_play><end_play>72.028061</end_play><video_information_id>24</video_information_id></multiple_entry><multiple_entry><start_play>106.9284</start_play><end_play>108.460307</end_play><video_information_id>24</video_information_id></multiple_entry><multiple_entry><start_play>142.5712</start_play><end_play>146.378569</end_play><video_information_id>24</video_information_id></multiple_entry></played_interval><playback_quality><timestamp_of_quality>1443443166145</timestamp_of_quality><current_video_position>0</current_video_position><video_width>1920</video_width><video_height>1080</video_height><video_information_id>24</video_information_id></playback_quality><network_state><timestamp_of_network_state>1443443166146</timestamp_of_network_state><current_video_position>143.220785</current_video_position><state>1</state><video_information_id>24</video_information_id></network_state><mute_state><timestamp_of_mute_state>1443443166146</timestamp_of_mute_state><current_video_position>143.220785</current_video_position><state>0</state><video_information_id>24</video_information_id></mute_state><length_of_stall><timestamp_of_stall>1443443165246</timestamp_of_stall><current_video_position>142.5712</current_video_position><duration_of_stall>0.263</duration_of_stall><video_information_id>24</video_information_id></length_of_stall><frame_per_second><multiple_entry><timestamp_of_frame>1443443166146</timestamp_of_frame><current_video_position>143.220785</current_video_position><number_of_frames>325</number_of_frames><video_information_id>24</video_information_id></multiple_entry><multiple_entry><timestamp_of_frame>1443443167146</timestamp_of_frame><current_video_position>144.242421</current_video_position><number_of_frames>25</number_of_frames><video_information_id>24</video_information_id></multiple_entry><multiple_entry><timestamp_of_frame>1443443168146</timestamp_of_frame><current_video_position>145.240838</current_video_position><number_of_frames>25</number_of_frames><video_information_id>24</video_information_id></multiple_entry><multiple_entry><timestamp_of_frame>1443443169147</timestamp_of_frame><current_video_position>146.239255</current_video_position><number_of_frames>25</number_of_frames><video_information_id>24</video_information_id></multiple_entry></frame_per_second><buffer_interval><start_buffer_time>0</start_buffer_time><end_buffer_time>178.214</end_buffer_time><video_information_id>24</video_information_id></buffer_interval></results></report>